[
    {
        "type": "flex",
        "altText": "ขับเคลื่อนการเติบโต EEC อย่างมีคุณภาพด้วยกลยุทธ์การแข่งขันแบบร่วมมือ (Coopetition)",
        "contents": {
  "type": "bubble",
  "size": "giga",
  "hero": {
    "type": "image",
    "url": "https://raw.githubusercontent.com/scbeic/sharetarget2/main/coopetitionLineOA.jpg",
    "size": "full",
    "aspectRatio": "20:14",
    "aspectMode": "cover",
    "action": {
      "type": "uri",
      "uri": "https://bit.ly/SMARTEEC_OCT_2024"
    }
  },
  "body": {
    "type": "box",
    "layout": "vertical",
    "contents": [
      {
        "type": "text",
        "text": "Key summary",
        "weight": "bold",
        "size": "lg"
      },
      {
        "type": "box",
        "layout": "vertical",
        "margin": "lg",
        "spacing": "sm",
        "contents": [
          {
            "type": "box",
            "layout": "baseline",
            "spacing": "sm",
            "contents": [
              {
                "type": "text",
                "text": "Coopetition คือการผสมผสานระหว่างความร่วมมือและการแข่งขัน ซึ่งเป็นการสร้างความร่วมมือเชิงกลยุทธ์ระหว่างผู้มีส่วนได้ส่วนเสียหลายกลุ่ม เพื่อเปลี่ยนคู่แข่ง ให้เป็นพันธมิตร ในการแก้ไขปัญหาที่ซับซ้อนและสร้างคุณค่าใหม่ให้เกิดประโยชน์ร่วมกัน",
                "wrap": true,
                "color": "#666666",
                "size": "sm",
                "flex": 5
              }
            ]
          }
        ]
      }
    ]
  },
  "footer": {
    "type": "box",
    "layout": "vertical",
    "spacing": "sm",
    "contents": [
      {
        "type": "button",
        "style": "primary",
        "height": "sm",
        "action": {
          "type": "uri",
          "label": "Read more",
          "uri": "https://bit.ly/SMARTEEC_OCT_2024"
        },
        "color": "#4e2e79"
      },
      {
        "type": "button",
        "style": "secondary",
        "height": "sm",
        "action": {
          "type": "uri",
          "label": "Share",
          "uri": "https://liff.line.me/1657155025-N4RBzQGX?messages=https://raw.githubusercontent.com/scbeic/sharetarget2/main/messages25102024.json"
        }
      },
      {
        "type": "box",
        "layout": "vertical",
        "contents": [],
        "margin": "sm"
      }
    ],
    "flex": 0
  }
}
    }
]
