[
    {
        "type": "flex",
        "altText": "[Full report] Outlook ไตรมาส 4/2024",
        "contents": 
    {
  "type": "bubble",
  "size": "giga",
  "hero": {
    "type": "image",
    "url": "https://raw.githubusercontent.com/scbeic/sharetarget2/main/outlook-fullreport-4q24_LineOA.jpg",
    "size": "full",
    "aspectRatio": "25:28",
    "aspectMode": "cover",
    "action": {
      "type": "uri",
      "uri": "https://bit.ly/Thai-Economy-SCBEIC"
    }
  },
  "footer": {
    "type": "box",
    "layout": "vertical",
    "spacing": "sm",
    "contents": [
      {
        "type": "button",
        "style": "primary",
        "height": "sm",
        "action": {
          "type": "uri",
          "label": "Read more",
          "uri": "https://bit.ly/Thai-Economy-SCBEIC"
        },
        "color": "#bd8c66"
      },
      {
        "type": "button",
        "style": "secondary",
        "height": "sm",
        "action": {
          "type": "uri",
          "label": "Share",
          "uri": "https://liff.line.me/1657155025-N4RBzQGX?messages=https://raw.githubusercontent.com/scbeic/sharetarget2/main/messages25122024.json"
        }
      },
      {
        "type": "box",
        "layout": "vertical",
        "contents": [],
        "margin": "sm"
      }
    ],
    "flex": 0,
    "backgroundColor": "#1f172b"
  }
}
 }       
]
